pygitmate/__init__.py
pygitmate/console.py
pygitmate/main.py
pygitmate/utils.py
pygitmate-0.1.4.dist-info/METADATA
pygitmate-0.1.4.dist-info/WHEEL
pygitmate-0.1.4.dist-info/entry_points.txt
pygitmate-0.1.4.dist-info/licenses/LICENSE
pygitmate-0.1.4.dist-info/RECORD
