Metadata-Version: 2.4
Name: pygitmate
Version: 0.1.4
Summary: A CLI tool to simplify Git workflows
Project-URL: homepage, https://github.com/sarvesh4396/pygitmate
Project-URL: repository, https://github.com/sarvesh4396/pygitmate
Project-URL: documentation, https://pypi.org/project/pygitmate/
Author-email: Sarvesh Kumar Dwivedi <heysarvesh@pm.me>
License-File: LICENSE
Keywords: agile,cli,developer-tools,git
Classifier: Development Status :: 3 - Alpha
Classifier: Intended Audience :: Developers
Classifier: License :: OSI Approved :: MIT License
Classifier: Programming Language :: Python :: 3
Classifier: Programming Language :: Python :: 3.12
Requires-Python: >=3.11
Requires-Dist: click>=8.1.7
Requires-Dist: gitpython>=3.1.43
Requires-Dist: rich>=13.9.2
